Metadata-Version: 1.1
Name: MolMod-amg
Version: 0.0.3
Summary: Manager for QC calculations
Home-page: UNKNOWN
Author: Andriy Zhugayevych, Sergey Matveev, Dmitry Aksenov
Author-email: UNKNOWN
License: GPL
Keywords: Density Functional Theory Crystal modeling
Platform: UNKNOWN
Classifier: Programming Language :: Python :: 3
Classifier: License :: OSI Approved :: GNU General Public License (GPL)
Classifier: Operating System :: OS Independent
